MANIFEST.in
README.txt
setup.cfg
setup.py
docs/HISTORY.txt
docs/INSTALL.txt
docs/LICENSE.GPL
docs/LICENSE.txt
ityou/__init__.py
ityou.thumbnails.egg-info/PKG-INFO
ityou.thumbnails.egg-info/SOURCES.txt
ityou.thumbnails.egg-info/dependency_links.txt
ityou.thumbnails.egg-info/entry_points.txt
ityou.thumbnails.egg-info/namespace_packages.txt
ityou.thumbnails.egg-info/not-zip-safe
ityou.thumbnails.egg-info/paster_plugins.txt
ityou.thumbnails.egg-info/requires.txt
ityou.thumbnails.egg-info/top_level.txt
ityou/thumbnails/__init__.py
ityou/thumbnails/configure.zcml
ityou/thumbnails/interfaces.py
ityou/thumbnails/tests.py
ityou/thumbnails/thumbnail.py
ityou/thumbnails/translate.sh
ityou/thumbnails/Extensions/Install.py
ityou/thumbnails/Extensions/__init__.py
ityou/thumbnails/browser/__init__.py
ityou/thumbnails/browser/ajax_get_thumbnail.py
ityou/thumbnails/browser/configure.zcml
ityou/thumbnails/browser/controlpanel.py
ityou/thumbnails/browser/show_preview.py
ityou/thumbnails/browser/show_thumbnail.py
ityou/thumbnails/browser/thumbnail_listing.py
ityou/thumbnails/browser/viewlets.py
ityou/thumbnails/browser/images/FolderDocuments.png
ityou/thumbnails/browser/images/FolderDocuments2.png
ityou/thumbnails/browser/images/down.png
ityou/thumbnails/browser/images/folder-thumbnail.png
ityou/thumbnails/browser/images/ityou-esi-thumbnails-icon.png
ityou/thumbnails/browser/images/no-thumbnail.png
ityou/thumbnails/browser/javascripts/#thumbnails.js
ityou/thumbnails/browser/javascripts/_jquery.inview.js
ityou/thumbnails/browser/javascripts/_thumbnails.js
ityou/thumbnails/browser/javascripts/thumbnail-viewlet.js
ityou/thumbnails/browser/stylesheets/thumbnails.css
ityou/thumbnails/browser/templates/show_preview.pt
ityou/thumbnails/browser/templates/thumbnail.pt
ityou/thumbnails/browser/templates/thumbnail_listing.pt
ityou/thumbnails/locales/ityou.thumbnails.pot
ityou/thumbnails/locales/plone.pot
ityou/thumbnails/locales/de/LC_MESSAGES/ityou.thumbnails.po
ityou/thumbnails/locales/de/LC_MESSAGES/plone.po
ityou/thumbnails/locales/en/LC_MESSAGES/ityou.thumbnails.po
ityou/thumbnails/locales/en/LC_MESSAGES/plone.po
ityou/thumbnails/profiles/default/browserlayer.xml
ityou/thumbnails/profiles/default/controlpanel.xml
ityou/thumbnails/profiles/default/cssregistry.xml
ityou/thumbnails/profiles/default/jsregistry.xml
ityou/thumbnails/profiles/default/metadata.xml
